eximreservoirsimulation/__init__.py
eximreservoirsimulation/explicit_and_implicit.py
eximreservoirsimulation/explicit_and_implicit_with_UI.py
eximreservoirsimulation/main.py
eximreservoirsimulation-0.0.4.dist-info/LICENSE
eximreservoirsimulation-0.0.4.dist-info/METADATA
eximreservoirsimulation-0.0.4.dist-info/WHEEL
eximreservoirsimulation-0.0.4.dist-info/entry_points.txt
eximreservoirsimulation-0.0.4.dist-info/top_level.txt
eximreservoirsimulation-0.0.4.dist-info/RECORD
