Metadata-Version: 2.1
Name: eximreservoirsimulation
Version: 0.0.4
Summary: Explicit and Implicit Reservoir Simulation Solver
Author-email: Muhammad Adhim Mulia <adhimmuliam@gmail.com>
Project-URL: Homepage, https://github.com/adhimmulia/ExImReservoirSimulation
Keywords: Explicit Reservoir Simulation, Implicit Reservoir Simulation, Reservoir Simulation
Classifier: Programming Language :: Python
Requires-Python: >=3.11
License-File: LICENSE
Requires-Dist: numpy
Requires-Dist: pandas
Requires-Dist: plotly
Requires-Dist: streamlit
Requires-Dist: dateutils
Requires-Dist: click
